bluesky_cmds/VERSION
bluesky_cmds/__init__.py
bluesky_cmds/__main__.py
bluesky_cmds/__version__.py
bluesky_cmds/_app.py
bluesky_cmds/_main_window.py
bluesky_cmds/_plot.py
bluesky_cmds/config-template.toml
bluesky_cmds/logging.py
bluesky_cmds/project/__init__.py
bluesky_cmds/project/classes.py
bluesky_cmds/project/colors.py
bluesky_cmds/project/project_globals.py
bluesky_cmds/project/style.py
bluesky_cmds/project/widgets.py
bluesky_cmds/project/widget files/checkbox_checked.png
bluesky_cmds/project/widget files/checkbox_unchecked.png
bluesky_cmds/somatic/__init__.py
bluesky_cmds/somatic/comms.py
bluesky_cmds/somatic/plan_ui.py
bluesky_cmds/somatic/presets.py
bluesky_cmds/somatic/queue.py
bluesky_cmds/somatic/signals.py
bluesky_cmds-2022.7.0.dist-info/entry_points.txt
bluesky_cmds-2022.7.0.dist-info/LICENSE
bluesky_cmds-2022.7.0.dist-info/WHEEL
bluesky_cmds-2022.7.0.dist-info/METADATA
bluesky_cmds-2022.7.0.dist-info/RECORD
