Metadata-Version: 2.1
Name: bluesky-cmds
Version: 2022.7.0
Summary: Custom interface to bluesky-queueserver used by the Wright Group
Home-page: https://github.com/wright-group/bluesky-cmds
Author: Blaise Thompson
Author-email: blaise@untzag.com
Requires-Python: >=3.7
Classifier: License :: OSI Approved :: MIT License
Requires-Dist: appdirs
Requires-Dist: bluesky-queueserver-api
Requires-Dist: click
Requires-Dist: pyqtgraph
Requires-Dist: pyside2
Requires-Dist: qtpy
Requires-Dist: toml
Requires-Dist: toolz
Requires-Dist: wrighttools
